langgraph/config.py
langgraph/constants.py
langgraph/errors.py
langgraph/py.typed
langgraph/types.py
langgraph/version.py
langgraph/_api/__init__.py
langgraph/_api/deprecation.py
langgraph/channels/__init__.py
langgraph/channels/any_value.py
langgraph/channels/base.py
langgraph/channels/binop.py
langgraph/channels/context.py
langgraph/channels/dynamic_barrier_value.py
langgraph/channels/ephemeral_value.py
langgraph/channels/last_value.py
langgraph/channels/named_barrier_value.py
langgraph/channels/py.typed
langgraph/channels/topic.py
langgraph/channels/untracked_value.py
langgraph/func/__init__.py
langgraph/func/py.typed
langgraph/graph/__init__.py
langgraph/graph/branch.py
langgraph/graph/graph.py
langgraph/graph/message.py
langgraph/graph/py.typed
langgraph/graph/schema_utils.py
langgraph/graph/state.py
langgraph/graph/ui.py
langgraph/managed/__init__.py
langgraph/managed/base.py
langgraph/managed/context.py
langgraph/managed/is_last_step.py
langgraph/managed/py.typed
langgraph/managed/shared_value.py
langgraph/pregel/__init__.py
langgraph/pregel/algo.py
langgraph/pregel/call.py
langgraph/pregel/checkpoint.py
langgraph/pregel/debug.py
langgraph/pregel/draw.py
langgraph/pregel/executor.py
langgraph/pregel/io.py
langgraph/pregel/log.py
langgraph/pregel/loop.py
langgraph/pregel/manager.py
langgraph/pregel/messages.py
langgraph/pregel/protocol.py
langgraph/pregel/py.typed
langgraph/pregel/read.py
langgraph/pregel/remote.py
langgraph/pregel/retry.py
langgraph/pregel/runner.py
langgraph/pregel/types.py
langgraph/pregel/utils.py
langgraph/pregel/validate.py
langgraph/pregel/write.py
langgraph/utils/__init__.py
langgraph/utils/cache.py
langgraph/utils/config.py
langgraph/utils/fields.py
langgraph/utils/future.py
langgraph/utils/py.typed
langgraph/utils/pydantic.py
langgraph/utils/queue.py
langgraph/utils/runnable.py
langgraph-0.4.6.dist-info/METADATA
langgraph-0.4.6.dist-info/WHEEL
langgraph-0.4.6.dist-info/licenses/LICENSE
langgraph-0.4.6.dist-info/RECORD
