Metadata-Version: 2.4
Name: langgraph
Version: 0.4.6
Summary: Building stateful, multi-actor applications with LLMs
Project-URL: Repository, https://www.github.com/langchain-ai/langgraph
License-Expression: MIT
License-File: LICENSE
Requires-Python: >=3.9
Requires-Dist: langchain-core>=0.1
Requires-Dist: langgraph-checkpoint>=2.0.26
Requires-Dist: langgraph-prebuilt>=0.2.0
Requires-Dist: langgraph-sdk>=0.1.42
Requires-Dist: pydantic>=2.7.4
Requires-Dist: xxhash>=3.5.0
